email_notify/__init__.py
email_notify/core.py
email_notify/crypt.py
email_notify-1.0.5.dist-info/METADATA
email_notify-1.0.5.dist-info/WHEEL
email_notify-1.0.5.dist-info/top_level.txt
email_notify-1.0.5.dist-info/RECORD
