Metadata-Version: 2.1
Name: email_notify
Version: 1.0.5
Summary: Email notifications when a code block or function finishes or ends unexpectedly
Author: Chao-Ning Hu
Classifier: Programming Language :: Python :: 3
Classifier: Operating System :: OS Independent
Classifier: License :: OSI Approved :: MIT License
Classifier: Intended Audience :: Developers
Requires-Python: >=3.7
Requires-Dist: cryptography
